coinex/__init__.py
coinex/coinex.py
coinex.py-1.0.4.dist-info/LICENSE
coinex.py-1.0.4.dist-info/METADATA
coinex.py-1.0.4.dist-info/WHEEL
coinex.py-1.0.4.dist-info/top_level.txt
coinex.py-1.0.4.dist-info/RECORD
