Metadata-Version: 2.1
Name: coinex.py
Version: 1.0.4
Summary: coinex.com API wrapper
Home-page: https://github.com/EchterAgo/coinex
Author: Axel Gembe
Author-email: derago@gmail.com
License: UNKNOWN
Platform: UNKNOWN
Classifier: Programming Language :: Python :: 3
Classifier: License :: OSI Approved :: MIT License
Classifier: Operating System :: OS Independent
Requires-Dist: requests
